quartet_qat/__init__.py
quartet_qat/module/__init__.py
quartet_qat/module/linear.py
quartet_qat/module/linear_fns.py
quartet_qat/utils/__init__.py
quartet_qat/utils/config.py
quartet_qat/utils/replace.py
quartet_qat-0.1.0.dist-info/METADATA
quartet_qat-0.1.0.dist-info/WHEEL
quartet_qat-0.1.0.dist-info/top_level.txt
quartet_qat-0.1.0.dist-info/RECORD
